{
  "name": "barsloader",
  "title": "Bars Loader",
  "category": "loader",
  "description": "A premium, animated Bars Loader component built with React, Framer Motion, and Tailwind CSS.",
  "isPro": false,
  "dialects": {
    "tsx": {
      "language": "tsx",
      "files": [
        {
          "name": "BarsLoader.tsx",
          "content": "\"use client\";\n\nimport React from 'react';\nimport { cn } from \"@/lib/utils\";\n\nexport interface BarsLoaderProps {\n  /** Number of bars */\n  count?: number;\n  /** Bar width in pixels */\n  barWidth?: number;\n  /** Bar height in pixels */\n  barHeight?: number;\n  /** Bar color */\n  color?: string;\n  /** Animation speed in seconds */\n  speed?: number;\n  /** Accessible label */\n  label?: string;\n  className?: string;\n}\n\nexport const BarsLoader = React.forwardRef<any, BarsLoaderProps>(({ count = 4, barWidth = 10, barHeight = 60, color = 'rgb(245, 158, 11)', speed = 1, label = 'Loading', className = '', ...props }, ref) => {\n        return (\n        <div ref={ref} {...props} className={cn(className)} \n          className={`inline-flex items-center gap-[3px] ${className}`}\n          role=\"status\"\n          aria-label={label}\n        >\n          {Array.from({ length: count }).map((_, i) => (\n            <span\n              key={i}\n              className=\"inline-block rounded-[2px]\"\n              style={{\n                width: barWidth,\n                height: barHeight,\n                backgroundColor: color,\n                animation: `loaderStretch ${speed}s ease infinite`,\n                animationDelay: `${i * (speed / count)}s`,\n              }}\n              aria-hidden=\"true\"\n            />\n          ))}\n          <span className=\"sr-only\">{label}</span>\n        </div>\n        );\n        });\n"
        }
      ],
      "dependencies": []
    },
    "jsx": {
      "language": "jsx",
      "files": [
        {
          "name": "BarsLoader.jsx",
          "content": "\"use client\";\n\nimport React from 'react';\nimport { cn } from \"@/lib/utils\";\n\n  /** Bar width in pixels */\n  barWidth?;\n  /** Bar height in pixels */\n  barHeight?;\n  /** Bar color */\n  color?;\n  /** Animation speed in seconds */\n  speed?;\n  /** Accessible label */\n  label?;\n  className?;\n}\n\nexport const BarsLoader = React.forwardRef<any, BarsLoaderProps>(({ count = 4, barWidth = 10, barHeight = 60, color = 'rgb(245, 158, 11)', speed = 1, label = 'Loading', className = '', ...props }, ref) => {\n        return (\n        <div ref={ref} {...props} className={cn(className)} \n          className={`inline-flex items-center gap-[3px] ${className}`}\n          role=\"status\"\n          aria-label={label}\n        >\n          {Array.from({ length: count }).map((_, i) => (\n            <span\n              key={i}\n              className=\"inline-block rounded-[2px]\"\n              style={{\n                width: barWidth,\n                height: barHeight,\n                backgroundColor: color,\n                animation: `loaderStretch ${speed}s ease infinite`,\n                animationDelay: `${i * (speed / count)}s`,\n              }}\n              aria-hidden=\"true\"\n            />\n          ))}\n          <span className=\"sr-only\">{label}</span>\n        </div>\n        );\n        });"
        }
      ],
      "dependencies": []
    }
  },
  "preview": {}
}